{
  "players": [
    {
      "id": "AJ Hammons - 1627773",
      "name": "AJ Hammons"
    },
    {
      "id": "Aaron Brooks - 201166",
      "name": "Aaron Brooks"
    },
    {
      "id": "Aaron Gordon - 203932",
      "name": "Aaron Gordon"
    },
    {
      "id": "Aaron Harrison - 1626151",
      "name": "Aaron Harrison"
    },
    {
      "id": "Adreian Payne - 203940",
      "name": "Adreian Payne"
    },
    {
      "id": "Al Horford - 201143",
      "name": "Al Horford"
    },
    {
      "id": "Al Jefferson - 2744",
      "name": "Al Jefferson"
    },
    {
      "id": "Al-Farouq Aminu - 202329",
      "name": "Al-Farouq Aminu"
    },
    {
      "id": "Alan Anderson - 101187",
      "name": "Alan Anderson"
    },
    {
      "id": "Alan Williams - 1626210",
      "name": "Alan Williams"
    },
    {
      "id": "Alec Burks - 202692",
      "name": "Alec Burks"
    },
    {
      "id": "Alex Abrines - 203518",
      "name": "Alex Abrines"
    },
    {
      "id": "Alex Len - 203458",
      "name": "Alex Len"
    },
    {
      "id": "Alex Poythress - 1627816",
      "name": "Alex Poythress"
    },
    {
      "id": "Alexis Ajinca - 201582",
      "name": "Alexis Ajinca"
    },
    {
      "id": "Allen Crabbe - 203459",
      "name": "Allen Crabbe"
    },
    {
      "id": "Alonzo Gee - 202087",
      "name": "Alonzo Gee"
    },
    {
      "id": "Amir Johnson - 101161",
      "name": "Amir Johnson"
    },
    {
      "id": "Anderson Varejao - 2760",
      "name": "Anderson Varejao"
    },
    {
      "id": "Andre Drummond - 203083",
      "name": "Andre Drummond"
    },
    {
      "id": "Andre Iguodala - 2738",
      "name": "Andre Iguodala"
    },
    {
      "id": "Andre Roberson - 203460",
      "name": "Andre Roberson"
    },
    {
      "id": "Andrew Bogut - 101106",
      "name": "Andrew Bogut"
    },
    {
      "id": "Andrew Harrison - 1626150",
      "name": "Andrew Harrison"
    },
    {
      "id": "Andrew Nicholson - 203094",
      "name": "Andrew Nicholson"
    },
    {
      "id": "Andrew Wiggins - 203952",
      "name": "Andrew Wiggins"
    },
    {
      "id": "Anthony Bennett - 203461",
      "name": "Anthony Bennett"
    },
    {
      "id": "Anthony Brown - 1626148",
      "name": "Anthony Brown"
    },
    {
      "id": "Anthony Davis - 203076",
      "name": "Anthony Davis"
    },
    {
      "id": "Anthony Morrow - 201627",
      "name": "Anthony Morrow"
    },
    {
      "id": "Anthony Tolliver - 201229",
      "name": "Anthony Tolliver"
    },
    {
      "id": "Archie Goodwin - 203462",
      "name": "Archie Goodwin"
    },
    {
      "id": "Arinze Onuaku - 202620",
      "name": "Arinze Onuaku"
    },
    {
      "id": "Aron Baynes - 203382",
      "name": "Aron Baynes"
    },
    {
      "id": "Arron Afflalo - 201167",
      "name": "Arron Afflalo"
    },
    {
      "id": "Austin Rivers - 203085",
      "name": "Austin Rivers"
    },
    {
      "id": "Avery Bradley - 202340",
      "name": "Avery Bradley"
    },
    {
      "id": "Axel Toupane - 1626253",
      "name": "Axel Toupane"
    },
    {
      "id": "Ben Bentil - 1627791",
      "name": "Ben Bentil"
    },
    {
      "id": "Ben McLemore - 203463",
      "name": "Ben McLemore"
    },
    {
      "id": "Beno Udrih - 2757",
      "name": "Beno Udrih"
    },
    {
      "id": "Bismack Biyombo - 202687",
      "name": "Bismack Biyombo"
    },
    {
      "id": "Blake Griffin - 201933",
      "name": "Blake Griffin"
    },
    {
      "id": "Boban Marjanović - 1626246",
      "name": "Boban Marjanović"
    },
    {
      "id": "Bobby Brown - 201628",
      "name": "Bobby Brown"
    },
    {
      "id": "Bobby Portis - 1626171",
      "name": "Bobby Portis"
    },
    {
      "id": "Bojan Bogdanović - 202711",
      "name": "Bojan Bogdanović"
    },
    {
      "id": "Boris Diaw - 2564",
      "name": "Boris Diaw"
    },
    {
      "id": "Bradley Beal - 203078",
      "name": "Bradley Beal"
    },
    {
      "id": "Brandan Wright - 201148",
      "name": "Brandan Wright"
    },
    {
      "id": "Brandon Bass - 101138",
      "name": "Brandon Bass"
    },
    {
      "id": "Brandon Ingram - 1627742",
      "name": "Brandon Ingram"
    },
    {
      "id": "Brandon Jennings - 201943",
      "name": "Brandon Jennings"
    },
    {
      "id": "Brandon Knight - 202688",
      "name": "Brandon Knight"
    },
    {
      "id": "Brandon Rush - 201575",
      "name": "Brandon Rush"
    },
    {
      "id": "Brian Roberts - 203148",
      "name": "Brian Roberts"
    },
    {
      "id": "Briante Weber - 1627362",
      "name": "Briante Weber"
    },
    {
      "id": "Brice Johnson - 1627744",
      "name": "Brice Johnson"
    },
    {
      "id": "Brook Lopez - 201572",
      "name": "Brook Lopez"
    },
    {
      "id": "Bruno Caboclo - 203998",
      "name": "Bruno Caboclo"
    },
    {
      "id": "Bryn Forbes - 1627854",
      "name": "Bryn Forbes"
    },
    {
      "id": "Buddy Hield - 1627741",
      "name": "Buddy Hield"
    },
    {
      "id": "C.J. Watson - 201228",
      "name": "C.J. Watson"
    },
    {
      "id": "C.J. Wilcox - 203912",
      "name": "C.J. Wilcox"
    },
    {
      "id": "CJ McCollum - 203468",
      "name": "CJ McCollum"
    },
    {
      "id": "CJ Miles - 101139",
      "name": "CJ Miles"
    },
    {
      "id": "Cameron Payne - 1626166",
      "name": "Cameron Payne"
    },
    {
      "id": "Caris LeVert - 1627747",
      "name": "Caris LeVert"
    },
    {
      "id": "Carmelo Anthony - 2546",
      "name": "Carmelo Anthony"
    },
    {
      "id": "Chandler Parsons - 202718",
      "name": "Chandler Parsons"
    },
    {
      "id": "Channing Frye - 101112",
      "name": "Channing Frye"
    },
    {
      "id": "Chasson Randle - 1626184",
      "name": "Chasson Randle"
    },
    {
      "id": "Cheick Diallo - 1627767",
      "name": "Cheick Diallo"
    },
    {
      "id": "Chinanu Onuaku - 1627778",
      "name": "Chinanu Onuaku"
    },
    {
      "id": "Chris Andersen - 2365",
      "name": "Chris Andersen"
    },
    {
      "id": "Chris McCullough - 1626191",
      "name": "Chris McCullough"
    },
    {
      "id": "Chris Paul - 101108",
      "name": "Chris Paul"
    },
    {
      "id": "Christian Wood - 1626174",
      "name": "Christian Wood"
    },
    {
      "id": "Clint Capela - 203991",
      "name": "Clint Capela"
    },
    {
      "id": "Cody Zeller - 203469",
      "name": "Cody Zeller"
    },
    {
      "id": "Cole Aldrich - 202332",
      "name": "Cole Aldrich"
    },
    {
      "id": "Corey Brewer - 201147",
      "name": "Corey Brewer"
    },
    {
      "id": "Cory Joseph - 202709",
      "name": "Cory Joseph"
    },
    {
      "id": "Courtney Lee - 201584",
      "name": "Courtney Lee"
    },
    {
      "id": "Cristiano Felicio - 1626245",
      "name": "Cristiano Felicio"
    },
    {
      "id": "D'Angelo Russell - 1626156",
      "name": "D'Angelo Russell"
    },
    {
      "id": "D.J. Augustin - 201571",
      "name": "D.J. Augustin"
    },
    {
      "id": "Dahntay Jones - 2563",
      "name": "Dahntay Jones"
    },
    {
      "id": "Damian Jones - 1627745",
      "name": "Damian Jones"
    },
    {
      "id": "Damian Lillard - 203081",
      "name": "Damian Lillard"
    },
    {
      "id": "Damjan Rudez - 204014",
      "name": "Damjan Rudez"
    },
    {
      "id": "Daniel Ochefu - 1627849",
      "name": "Daniel Ochefu"
    },
    {
      "id": "Danilo Gallinari - 201568",
      "name": "Danilo Gallinari"
    },
    {
      "id": "Danny Green - 201980",
      "name": "Danny Green"
    },
    {
      "id": "Dante Cunningham - 201967",
      "name": "Dante Cunningham"
    },
    {
      "id": "Danté Exum - 203957",
      "name": "Danté Exum"
    },
    {
      "id": "Danuel House Jr. - 1627863",
      "name": "Danuel House Jr."
    },
    {
      "id": "Dario Šarić - 203967",
      "name": "Dario Šarić"
    },
    {
      "id": "Darrell Arthur - 201589",
      "name": "Darrell Arthur"
    },
    {
      "id": "Darren Collison - 201954",
      "name": "Darren Collison"
    },
    {
      "id": "Darrun Hilliard - 1626199",
      "name": "Darrun Hilliard"
    },
    {
      "id": "David Lee - 101135",
      "name": "David Lee"
    },
    {
      "id": "David Nwaba - 1628021",
      "name": "David Nwaba"
    },
    {
      "id": "David West - 2561",
      "name": "David West"
    },
    {
      "id": "DeAndre Jordan - 201599",
      "name": "DeAndre Jordan"
    },
    {
      "id": "DeAndre Liggins - 202732",
      "name": "DeAndre Liggins"
    },
    {
      "id": "DeAndre' Bembry - 1627761",
      "name": "DeAndre' Bembry"
    },
    {
      "id": "DeMar DeRozan - 201942",
      "name": "DeMar DeRozan"
    },
    {
      "id": "DeMarcus Cousins - 202326",
      "name": "DeMarcus Cousins"
    },
    {
      "id": "DeMarre Carroll - 201960",
      "name": "DeMarre Carroll"
    },
    {
      "id": "Dejounte Murray - 1627749",
      "name": "Dejounte Murray"
    },
    {
      "id": "Delon Wright - 1626153",
      "name": "Delon Wright"
    },
    {
      "id": "Demetrius Jackson - 1627743",
      "name": "Demetrius Jackson"
    },
    {
      "id": "Dennis Schröder - 203471",
      "name": "Dennis Schröder"
    },
    {
      "id": "Denzel Valentine - 1627756",
      "name": "Denzel Valentine"
    },
    {
      "id": "Deron Williams - 101114",
      "name": "Deron Williams"
    },
    {
      "id": "Derrick Favors - 202324",
      "name": "Derrick Favors"
    },
    {
      "id": "Derrick Jones Jr. - 1627884",
      "name": "Derrick Jones Jr."
    },
    {
      "id": "Derrick Rose - 201565",
      "name": "Derrick Rose"
    },
    {
      "id": "Derrick Williams - 202682",
      "name": "Derrick Williams"
    },
    {
      "id": "Devin Booker - 1626164",
      "name": "Devin Booker"
    },
    {
      "id": "Devin Harris - 2734",
      "name": "Devin Harris"
    },
    {
      "id": "Dewayne Dedmon - 203473",
      "name": "Dewayne Dedmon"
    },
    {
      "id": "Deyonta Davis - 1627738",
      "name": "Deyonta Davis"
    },
    {
      "id": "Diamond Stone - 1627754",
      "name": "Diamond Stone"
    },
    {
      "id": "Dion Waiters - 203079",
      "name": "Dion Waiters"
    },
    {
      "id": "Dirk Nowitzki - 1717",
      "name": "Dirk Nowitzki"
    },
    {
      "id": "Domantas Sabonis - 1627734",
      "name": "Domantas Sabonis"
    },
    {
      "id": "Donatas Motiejunas - 202700",
      "name": "Donatas Motiejunas"
    },
    {
      "id": "Dorian Finney-Smith - 1627827",
      "name": "Dorian Finney-Smith"
    },
    {
      "id": "Doug McDermott - 203926",
      "name": "Doug McDermott"
    },
    {
      "id": "Dragan Bender - 1627733",
      "name": "Dragan Bender"
    },
    {
      "id": "Draymond Green - 203110",
      "name": "Draymond Green"
    },
    {
      "id": "Dwight Howard - 2730",
      "name": "Dwight Howard"
    },
    {
      "id": "Dwight Powell - 203939",
      "name": "Dwight Powell"
    },
    {
      "id": "Dwyane Wade - 2548",
      "name": "Dwyane Wade"
    },
    {
      "id": "Dāvis Bertāns - 202722",
      "name": "Dāvis Bertāns"
    },
    {
      "id": "E'Twaun Moore - 202734",
      "name": "E'Twaun Moore"
    },
    {
      "id": "Ed Davis - 202334",
      "name": "Ed Davis"
    },
    {
      "id": "Edy Tavares - 204002",
      "name": "Edy Tavares"
    },
    {
      "id": "Elfrid Payton - 203901",
      "name": "Elfrid Payton"
    },
    {
      "id": "Elijah Millsap - 202407",
      "name": "Elijah Millsap"
    },
    {
      "id": "Emmanuel Mudiay - 1626144",
      "name": "Emmanuel Mudiay"
    },
    {
      "id": "Enes Freedom - 202683",
      "name": "Enes Freedom"
    },
    {
      "id": "Eric Bledsoe - 202339",
      "name": "Eric Bledsoe"
    },
    {
      "id": "Eric Gordon - 201569",
      "name": "Eric Gordon"
    },
    {
      "id": "Ersan Ilyasova - 101141",
      "name": "Ersan Ilyasova"
    },
    {
      "id": "Evan Fournier - 203095",
      "name": "Evan Fournier"
    },
    {
      "id": "Evan Turner - 202323",
      "name": "Evan Turner"
    },
    {
      "id": "Frank Kaminsky - 1626163",
      "name": "Frank Kaminsky"
    },
    {
      "id": "Fred VanVleet - 1627832",
      "name": "Fred VanVleet"
    },
    {
      "id": "Garrett Temple - 202066",
      "name": "Garrett Temple"
    },
    {
      "id": "Gary Harris - 203914",
      "name": "Gary Harris"
    },
    {
      "id": "Gary Neal - 202390",
      "name": "Gary Neal"
    },
    {
      "id": "Gary Payton II - 1627780",
      "name": "Gary Payton II"
    },
    {
      "id": "George Hill - 201588",
      "name": "George Hill"
    },
    {
      "id": "Georges Niang - 1627777",
      "name": "Georges Niang"
    },
    {
      "id": "Georgios Papagiannis - 1627834",
      "name": "Georgios Papagiannis"
    },
    {
      "id": "Gerald Green - 101123",
      "name": "Gerald Green"
    },
    {
      "id": "Gerald Henderson - 201945",
      "name": "Gerald Henderson"
    },
    {
      "id": "Giannis Antetokounmpo - 203507",
      "name": "Giannis Antetokounmpo"
    },
    {
      "id": "Glenn Robinson III - 203922",
      "name": "Glenn Robinson III"
    },
    {
      "id": "Goran Dragic - 201609",
      "name": "Goran Dragic"
    },
    {
      "id": "Gordon Hayward - 202330",
      "name": "Gordon Hayward"
    },
    {
      "id": "Gorgui Dieng - 203476",
      "name": "Gorgui Dieng"
    },
    {
      "id": "Greg Monroe - 202328",
      "name": "Greg Monroe"
    },
    {
      "id": "Greivis Vasquez - 202349",
      "name": "Greivis Vasquez"
    },
    {
      "id": "Harrison Barnes - 203084",
      "name": "Harrison Barnes"
    },
    {
      "id": "Hassan Whiteside - 202355",
      "name": "Hassan Whiteside"
    },
    {
      "id": "Henry Ellenson - 1627740",
      "name": "Henry Ellenson"
    },
    {
      "id": "Hollis Thompson - 203138",
      "name": "Hollis Thompson"
    },
    {
      "id": "Ian Clark - 203546",
      "name": "Ian Clark"
    },
    {
      "id": "Ian Mahinmi - 101133",
      "name": "Ian Mahinmi"
    },
    {
      "id": "Iman Shumpert - 202697",
      "name": "Iman Shumpert"
    },
    {
      "id": "Isaiah Canaan - 203477",
      "name": "Isaiah Canaan"
    },
    {
      "id": "Isaiah Taylor - 1627819",
      "name": "Isaiah Taylor"
    },
    {
      "id": "Isaiah Thomas - 202738",
      "name": "Isaiah Thomas"
    },
    {
      "id": "Isaiah Whitehead - 1627785",
      "name": "Isaiah Whitehead"
    },
    {
      "id": "Ish Smith - 202397",
      "name": "Ish Smith"
    },
    {
      "id": "Ivica Zubac - 1627826",
      "name": "Ivica Zubac"
    },
    {
      "id": "J.J. Barea - 200826",
      "name": "J.J. Barea"
    },
    {
      "id": "JJ Redick - 200755",
      "name": "JJ Redick"
    },
    {
      "id": "JR Smith - 2747",
      "name": "JR Smith"
    },
    {
      "id": "JaMychal Green - 203210",
      "name": "JaMychal Green"
    },
    {
      "id": "JaVale McGee - 201580",
      "name": "JaVale McGee"
    },
    {
      "id": "Jabari Parker - 203953",
      "name": "Jabari Parker"
    },
    {
      "id": "Jae Crowder - 203109",
      "name": "Jae Crowder"
    },
    {
      "id": "Jahlil Okafor - 1626143",
      "name": "Jahlil Okafor"
    },
    {
      "id": "Jake Layman - 1627774",
      "name": "Jake Layman"
    },
    {
      "id": "Jakob Poeltl - 1627751",
      "name": "Jakob Poeltl"
    },
    {
      "id": "Jamal Crawford - 2037",
      "name": "Jamal Crawford"
    },
    {
      "id": "Jamal Murray - 1627750",
      "name": "Jamal Murray"
    },
    {
      "id": "Jameer Nelson - 2749",
      "name": "Jameer Nelson"
    },
    {
      "id": "James Ennis III - 203516",
      "name": "James Ennis III"
    },
    {
      "id": "James Harden - 201935",
      "name": "James Harden"
    },
    {
      "id": "James Johnson - 201949",
      "name": "James Johnson"
    },
    {
      "id": "James Jones - 2592",
      "name": "James Jones"
    },
    {
      "id": "James Michael McAdoo - 203949",
      "name": "James Michael McAdoo"
    },
    {
      "id": "James Young - 203923",
      "name": "James Young"
    },
    {
      "id": "Jared Dudley - 201162",
      "name": "Jared Dudley"
    },
    {
      "id": "Jared Sullinger - 203096",
      "name": "Jared Sullinger"
    },
    {
      "id": "Jarell Eddie - 204067",
      "name": "Jarell Eddie"
    },
    {
      "id": "Jarell Martin - 1626185",
      "name": "Jarell Martin"
    },
    {
      "id": "Jarnell Stokes - 203950",
      "name": "Jarnell Stokes"
    },
    {
      "id": "Jarrett Jack - 101127",
      "name": "Jarrett Jack"
    },
    {
      "id": "Jarrod Uthoff - 1627784",
      "name": "Jarrod Uthoff"
    },
    {
      "id": "Jason Smith - 201160",
      "name": "Jason Smith"
    },
    {
      "id": "Jason Terry - 1891",
      "name": "Jason Terry"
    },
    {
      "id": "Jaylen Brown - 1627759",
      "name": "Jaylen Brown"
    },
    {
      "id": "Jeff Green - 201145",
      "name": "Jeff Green"
    },
    {
      "id": "Jeff Teague - 201952",
      "name": "Jeff Teague"
    },
    {
      "id": "Jeff Withey - 203481",
      "name": "Jeff Withey"
    },
    {
      "id": "Jerami Grant - 203924",
      "name": "Jerami Grant"
    },
    {
      "id": "Jeremy Lamb - 203087",
      "name": "Jeremy Lamb"
    },
    {
      "id": "Jeremy Lin - 202391",
      "name": "Jeremy Lin"
    },
    {
      "id": "Jerian Grant - 1626170",
      "name": "Jerian Grant"
    },
    {
      "id": "Jerryd Bayless - 201573",
      "name": "Jerryd Bayless"
    },
    {
      "id": "Jimmy Butler III - 202710",
      "name": "Jimmy Butler III"
    },
    {
      "id": "Joakim Noah - 201149",
      "name": "Joakim Noah"
    },
    {
      "id": "Jodie Meeks - 201975",
      "name": "Jodie Meeks"
    },
    {
      "id": "Joe Harris - 203925",
      "name": "Joe Harris"
    },
    {
      "id": "Joe Ingles - 204060",
      "name": "Joe Ingles"
    },
    {
      "id": "Joe Johnson - 2207",
      "name": "Joe Johnson"
    },
    {
      "id": "Joe Young - 1626202",
      "name": "Joe Young"
    },
    {
      "id": "Joel Anthony - 201202",
      "name": "Joel Anthony"
    },
    {
      "id": "Joel Bolomboy - 1627762",
      "name": "Joel Bolomboy"
    },
    {
      "id": "Joel Embiid - 203954",
      "name": "Joel Embiid"
    },
    {
      "id": "Joffrey Lauvergne - 203530",
      "name": "Joffrey Lauvergne"
    },
    {
      "id": "John Henson - 203089",
      "name": "John Henson"
    },
    {
      "id": "John Jenkins - 203098",
      "name": "John Jenkins"
    },
    {
      "id": "John Lucas III - 101249",
      "name": "John Lucas III"
    },
    {
      "id": "John Wall - 202322",
      "name": "John Wall"
    },
    {
      "id": "Johnny O'Bryant III - 203948",
      "name": "Johnny O'Bryant III"
    },
    {
      "id": "Jon Leuer - 202720",
      "name": "Jon Leuer"
    },
    {
      "id": "Jonas Jerebko - 201973",
      "name": "Jonas Jerebko"
    },
    {
      "id": "Jonas Valančiūnas - 202685",
      "name": "Jonas Valančiūnas"
    },
    {
      "id": "Jonathan Gibson - 1626780",
      "name": "Jonathan Gibson"
    },
    {
      "id": "Jonathon Simmons - 203613",
      "name": "Jonathon Simmons"
    },
    {
      "id": "Jordan Clarkson - 203903",
      "name": "Jordan Clarkson"
    },
    {
      "id": "Jordan Crawford - 202348",
      "name": "Jordan Crawford"
    },
    {
      "id": "Jordan Farmar - 200770",
      "name": "Jordan Farmar"
    },
    {
      "id": "Jordan Hill - 201941",
      "name": "Jordan Hill"
    },
    {
      "id": "Jordan McRae - 203895",
      "name": "Jordan McRae"
    },
    {
      "id": "Jordan Mickey - 1626175",
      "name": "Jordan Mickey"
    },
    {
      "id": "Jose Calderon - 101181",
      "name": "Jose Calderon"
    },
    {
      "id": "Josh Huestis - 203962",
      "name": "Josh Huestis"
    },
    {
      "id": "Josh McRoberts - 201177",
      "name": "Josh McRoberts"
    },
    {
      "id": "Josh Richardson - 1626196",
      "name": "Josh Richardson"
    },
    {
      "id": "Jrue Holiday - 201950",
      "name": "Jrue Holiday"
    },
    {
      "id": "Juancho Hernangomez - 1627823",
      "name": "Juancho Hernangomez"
    },
    {
      "id": "Julius Randle - 203944",
      "name": "Julius Randle"
    },
    {
      "id": "Justin Anderson - 1626147",
      "name": "Justin Anderson"
    },
    {
      "id": "Justin Hamilton - 203120",
      "name": "Justin Hamilton"
    },
    {
      "id": "Justin Harper - 202712",
      "name": "Justin Harper"
    },
    {
      "id": "Justin Holiday - 203200",
      "name": "Justin Holiday"
    },
    {
      "id": "Justise Winslow - 1626159",
      "name": "Justise Winslow"
    },
    {
      "id": "Jusuf Nurkić - 203994",
      "name": "Jusuf Nurkić"
    },
    {
      "id": "KJ McDaniels - 203909",
      "name": "KJ McDaniels"
    },
    {
      "id": "Karl-Anthony Towns - 1626157",
      "name": "Karl-Anthony Towns"
    },
    {
      "id": "Kawhi Leonard - 202695",
      "name": "Kawhi Leonard"
    },
    {
      "id": "Kay Felder - 1627770",
      "name": "Kay Felder"
    },
    {
      "id": "Kelly Olynyk - 203482",
      "name": "Kelly Olynyk"
    },
    {
      "id": "Kelly Oubre Jr. - 1626162",
      "name": "Kelly Oubre Jr."
    },
    {
      "id": "Kemba Walker - 202689",
      "name": "Kemba Walker"
    },
    {
      "id": "Kenneth Faried - 202702",
      "name": "Kenneth Faried"
    },
    {
      "id": "Kent Bazemore - 203145",
      "name": "Kent Bazemore"
    },
    {
      "id": "Kentavious Caldwell-Pope - 203484",
      "name": "Kentavious Caldwell-Pope"
    },
    {
      "id": "Kevin Durant - 201142",
      "name": "Kevin Durant"
    },
    {
      "id": "Kevin Love - 201567",
      "name": "Kevin Love"
    },
    {
      "id": "Kevin Seraphin - 202338",
      "name": "Kevin Seraphin"
    },
    {
      "id": "Kevon Looney - 1626172",
      "name": "Kevon Looney"
    },
    {
      "id": "Khris Middleton - 203114",
      "name": "Khris Middleton"
    },
    {
      "id": "Klay Thompson - 202691",
      "name": "Klay Thompson"
    },
    {
      "id": "Kosta Koufos - 201585",
      "name": "Kosta Koufos"
    },
    {
      "id": "Kris Dunn - 1627739",
      "name": "Kris Dunn"
    },
    {
      "id": "Kris Humphries - 2743",
      "name": "Kris Humphries"
    },
    {
      "id": "Kristaps Porziņģis - 204001",
      "name": "Kristaps Porziņģis"
    },
    {
      "id": "Kyle Anderson - 203937",
      "name": "Kyle Anderson"
    },
    {
      "id": "Kyle Korver - 2594",
      "name": "Kyle Korver"
    },
    {
      "id": "Kyle Lowry - 200768",
      "name": "Kyle Lowry"
    },
    {
      "id": "Kyle O'Quinn - 203124",
      "name": "Kyle O'Quinn"
    },
    {
      "id": "Kyle Singler - 202713",
      "name": "Kyle Singler"
    },
    {
      "id": "Kyle Wiltjer - 1627787",
      "name": "Kyle Wiltjer"
    },
    {
      "id": "Kyrie Irving - 202681",
      "name": "Kyrie Irving"
    },
    {
      "id": "LaMarcus Aldridge - 200746",
      "name": "LaMarcus Aldridge"
    },
    {
      "id": "Lamar Patterson - 203934",
      "name": "Lamar Patterson"
    },
    {
      "id": "Lance Stephenson - 202362",
      "name": "Lance Stephenson"
    },
    {
      "id": "Lance Thomas - 202498",
      "name": "Lance Thomas"
    },
    {
      "id": "Langston Galloway - 204038",
      "name": "Langston Galloway"
    },
    {
      "id": "Larry Nance Jr. - 1626204",
      "name": "Larry Nance Jr."
    },
    {
      "id": "Larry Sanders - 202336",
      "name": "Larry Sanders"
    },
    {
      "id": "Lavoy Allen - 202730",
      "name": "Lavoy Allen"
    },
    {
      "id": "LeBron James - 2544",
      "name": "LeBron James"
    },
    {
      "id": "Leandro Barbosa - 2571",
      "name": "Leandro Barbosa"
    },
    {
      "id": "Lou Williams - 101150",
      "name": "Lou Williams"
    },
    {
      "id": "Luc Mbah a Moute - 201601",
      "name": "Luc Mbah a Moute"
    },
    {
      "id": "Lucas Nogueira - 203512",
      "name": "Lucas Nogueira"
    },
    {
      "id": "Luis Scola - 2449",
      "name": "Luis Scola"
    },
    {
      "id": "Luke Babbitt - 202337",
      "name": "Luke Babbitt"
    },
    {
      "id": "Luol Deng - 2736",
      "name": "Luol Deng"
    },
    {
      "id": "Malachi Richardson - 1627781",
      "name": "Malachi Richardson"
    },
    {
      "id": "Malcolm Brogdon - 1627763",
      "name": "Malcolm Brogdon"
    },
    {
      "id": "Malcolm Delaney - 1627098",
      "name": "Malcolm Delaney"
    },
    {
      "id": "Malik Beasley - 1627736",
      "name": "Malik Beasley"
    },
    {
      "id": "Manny Harris - 202412",
      "name": "Manny Harris"
    },
    {
      "id": "Manu Ginobili - 1938",
      "name": "Manu Ginobili"
    },
    {
      "id": "Marc Gasol - 201188",
      "name": "Marc Gasol"
    },
    {
      "id": "Marcelo Huertas - 1626273",
      "name": "Marcelo Huertas"
    },
    {
      "id": "Marcin Gortat - 101162",
      "name": "Marcin Gortat"
    },
    {
      "id": "Marco Belinelli - 201158",
      "name": "Marco Belinelli"
    },
    {
      "id": "Marcus Georges-Hunt - 1627875",
      "name": "Marcus Georges-Hunt"
    },
    {
      "id": "Marcus Morris Sr. - 202694",
      "name": "Marcus Morris Sr."
    },
    {
      "id": "Marcus Smart - 203935",
      "name": "Marcus Smart"
    },
    {
      "id": "Marcus Thornton - 201977",
      "name": "Marcus Thornton"
    },
    {
      "id": "Mario Hezonja - 1626209",
      "name": "Mario Hezonja"
    },
    {
      "id": "Markieff Morris - 202693",
      "name": "Markieff Morris"
    },
    {
      "id": "Marquese Chriss - 1627737",
      "name": "Marquese Chriss"
    },
    {
      "id": "Marreese Speights - 201578",
      "name": "Marreese Speights"
    },
    {
      "id": "Marshall Plumlee - 1627850",
      "name": "Marshall Plumlee"
    },
    {
      "id": "Marvin Williams - 101107",
      "name": "Marvin Williams"
    },
    {
      "id": "Mason Plumlee - 203486",
      "name": "Mason Plumlee"
    },
    {
      "id": "Matt Barnes - 2440",
      "name": "Matt Barnes"
    },
    {
      "id": "Matthew Dellavedova - 203521",
      "name": "Matthew Dellavedova"
    },
    {
      "id": "Maurice Harkless - 203090",
      "name": "Maurice Harkless"
    },
    {
      "id": "Maurice Ndour - 1626254",
      "name": "Maurice Ndour"
    },
    {
      "id": "Metta World Peace - 1897",
      "name": "Metta World Peace"
    },
    {
      "id": "Meyers Leonard - 203086",
      "name": "Meyers Leonard"
    },
    {
      "id": "Michael Beasley - 201563",
      "name": "Michael Beasley"
    },
    {
      "id": "Michael Carter-Williams - 203487",
      "name": "Michael Carter-Williams"
    },
    {
      "id": "Michael Gbinije - 1627771",
      "name": "Michael Gbinije"
    },
    {
      "id": "Michael Kidd-Gilchrist - 203077",
      "name": "Michael Kidd-Gilchrist"
    },
    {
      "id": "Mike Conley - 201144",
      "name": "Mike Conley"
    },
    {
      "id": "Mike Dunleavy - 2399",
      "name": "Mike Dunleavy"
    },
    {
      "id": "Mike Miller - 2034",
      "name": "Mike Miller"
    },
    {
      "id": "Mike Muscala - 203488",
      "name": "Mike Muscala"
    },
    {
      "id": "Mike Scott - 203118",
      "name": "Mike Scott"
    },
    {
      "id": "Mike Tobey - 1627861",
      "name": "Mike Tobey"
    },
    {
      "id": "Miles Plumlee - 203101",
      "name": "Miles Plumlee"
    },
    {
      "id": "Mindaugas Kuzminskas - 1627851",
      "name": "Mindaugas Kuzminskas"
    },
    {
      "id": "Mirza Teletovic - 203141",
      "name": "Mirza Teletovic"
    },
    {
      "id": "Monta Ellis - 101145",
      "name": "Monta Ellis"
    },
    {
      "id": "Montrezl Harrell - 1626149",
      "name": "Montrezl Harrell"
    },
    {
      "id": "Myles Turner - 1626167",
      "name": "Myles Turner"
    },
    {
      "id": "Nemanja Bjelica - 202357",
      "name": "Nemanja Bjelica"
    },
    {
      "id": "Nene - 2403",
      "name": "Nene"
    },
    {
      "id": "Nerlens Noel - 203457",
      "name": "Nerlens Noel"
    },
    {
      "id": "Nick Collison - 2555",
      "name": "Nick Collison"
    },
    {
      "id": "Nick Young - 201156",
      "name": "Nick Young"
    },
    {
      "id": "Nicolas Batum - 201587",
      "name": "Nicolas Batum"
    },
    {
      "id": "Nicolas Brussino - 1627852",
      "name": "Nicolas Brussino"
    },
    {
      "id": "Nicolas Laprovittola - 1627879",
      "name": "Nicolas Laprovittola"
    },
    {
      "id": "Nik Stauskas - 203917",
      "name": "Nik Stauskas"
    },
    {
      "id": "Nikola Jokić - 203999",
      "name": "Nikola Jokić"
    },
    {
      "id": "Nikola Mirotic - 202703",
      "name": "Nikola Mirotic"
    },
    {
      "id": "Nikola Vučević - 202696",
      "name": "Nikola Vučević"
    },
    {
      "id": "Noah Vonleh - 203943",
      "name": "Noah Vonleh"
    },
    {
      "id": "Norman Powell - 1626181",
      "name": "Norman Powell"
    },
    {
      "id": "Norris Cole - 202708",
      "name": "Norris Cole"
    },
    {
      "id": "Okaro White - 1627855",
      "name": "Okaro White"
    },
    {
      "id": "Omer Asik - 201600",
      "name": "Omer Asik"
    },
    {
      "id": "Omri Casspi - 201956",
      "name": "Omri Casspi"
    },
    {
      "id": "Otto Porter Jr. - 203490",
      "name": "Otto Porter Jr."
    },
    {
      "id": "P.J. Tucker - 200782",
      "name": "P.J. Tucker"
    },
    {
      "id": "Pascal Siakam - 1627783",
      "name": "Pascal Siakam"
    },
    {
      "id": "Pat Connaughton - 1626192",
      "name": "Pat Connaughton"
    },
    {
      "id": "Patricio Garino - 1627868",
      "name": "Patricio Garino"
    },
    {
      "id": "Patrick Beverley - 201976",
      "name": "Patrick Beverley"
    },
    {
      "id": "Patrick McCaw - 1627775",
      "name": "Patrick McCaw"
    },
    {
      "id": "Patrick Patterson - 202335",
      "name": "Patrick Patterson"
    },
    {
      "id": "Patty Mills - 201988",
      "name": "Patty Mills"
    },
    {
      "id": "Pau Gasol - 2200",
      "name": "Pau Gasol"
    },
    {
      "id": "Paul George - 202331",
      "name": "Paul George"
    },
    {
      "id": "Paul Millsap - 200794",
      "name": "Paul Millsap"
    },
    {
      "id": "Paul Pierce - 1718",
      "name": "Paul Pierce"
    },
    {
      "id": "Paul Zipser - 1627835",
      "name": "Paul Zipser"
    },
    {
      "id": "Pierre Jackson - 203510",
      "name": "Pierre Jackson"
    },
    {
      "id": "Quincy Acy - 203112",
      "name": "Quincy Acy"
    },
    {
      "id": "Quinn Cook - 1626188",
      "name": "Quinn Cook"
    },
    {
      "id": "RJ Hunter - 1626154",
      "name": "RJ Hunter"
    },
    {
      "id": "Rajon Rondo - 200765",
      "name": "Rajon Rondo"
    },
    {
      "id": "Rakeem Christmas - 1626176",
      "name": "Rakeem Christmas"
    },
    {
      "id": "Ramon Sessions - 201196",
      "name": "Ramon Sessions"
    },
    {
      "id": "Randy Foye - 200751",
      "name": "Randy Foye"
    },
    {
      "id": "Rashad Vaughn - 1626173",
      "name": "Rashad Vaughn"
    },
    {
      "id": "Raul Neto - 203526",
      "name": "Raul Neto"
    },
    {
      "id": "Raymond Felton - 101109",
      "name": "Raymond Felton"
    },
    {
      "id": "Reggie Bullock Jr. - 203493",
      "name": "Reggie Bullock Jr."
    },
    {
      "id": "Reggie Jackson - 202704",
      "name": "Reggie Jackson"
    },
    {
      "id": "Reggie Williams - 202130",
      "name": "Reggie Williams"
    },
    {
      "id": "Richard Jefferson - 2210",
      "name": "Richard Jefferson"
    },
    {
      "id": "Richaun Holmes - 1626158",
      "name": "Richaun Holmes"
    },
    {
      "id": "Ricky Rubio - 201937",
      "name": "Ricky Rubio"
    },
    {
      "id": "Robert Covington - 203496",
      "name": "Robert Covington"
    },
    {
      "id": "Robin Lopez - 201577",
      "name": "Robin Lopez"
    },
    {
      "id": "Rodney Hood - 203918",
      "name": "Rodney Hood"
    },
    {
      "id": "Rodney McGruder - 203585",
      "name": "Rodney McGruder"
    },
    {
      "id": "Rodney Stuckey - 201155",
      "name": "Rodney Stuckey"
    },
    {
      "id": "Ron Baker - 1627758",
      "name": "Ron Baker"
    },
    {
      "id": "Rondae Hollis-Jefferson - 1626178",
      "name": "Rondae Hollis-Jefferson"
    },
    {
      "id": "Ronnie Price - 101179",
      "name": "Ronnie Price"
    },
    {
      "id": "Roy Hibbert - 201579",
      "name": "Roy Hibbert"
    },
    {
      "id": "Rudy Gay - 200752",
      "name": "Rudy Gay"
    },
    {
      "id": "Rudy Gobert - 203497",
      "name": "Rudy Gobert"
    },
    {
      "id": "Russell Westbrook - 201566",
      "name": "Russell Westbrook"
    },
    {
      "id": "Ryan Anderson - 201583",
      "name": "Ryan Anderson"
    },
    {
      "id": "Ryan Kelly - 203527",
      "name": "Ryan Kelly"
    },
    {
      "id": "Salah Mejri - 1626257",
      "name": "Salah Mejri"
    },
    {
      "id": "Sam Dekker - 1626155",
      "name": "Sam Dekker"
    },
    {
      "id": "Sasha Vujacic - 2756",
      "name": "Sasha Vujacic"
    },
    {
      "id": "Sean Kilpatrick - 203930",
      "name": "Sean Kilpatrick"
    },
    {
      "id": "Semaj Christon - 203902",
      "name": "Semaj Christon"
    },
    {
      "id": "Serge Ibaka - 201586",
      "name": "Serge Ibaka"
    },
    {
      "id": "Sergio Rodriguez - 200771",
      "name": "Sergio Rodriguez"
    },
    {
      "id": "Seth Curry - 203552",
      "name": "Seth Curry"
    },
    {
      "id": "Shabazz Muhammad - 203498",
      "name": "Shabazz Muhammad"
    },
    {
      "id": "Shabazz Napier - 203894",
      "name": "Shabazz Napier"
    },
    {
      "id": "Shaun Livingston - 2733",
      "name": "Shaun Livingston"
    },
    {
      "id": "Shawn Long - 1627848",
      "name": "Shawn Long"
    },
    {
      "id": "Sheldon Mac - 1627815",
      "name": "Sheldon Mac"
    },
    {
      "id": "Shelvin Mack - 202714",
      "name": "Shelvin Mack"
    },
    {
      "id": "Skal Labissiere - 1627746",
      "name": "Skal Labissiere"
    },
    {
      "id": "Solomon Hill - 203524",
      "name": "Solomon Hill"
    },
    {
      "id": "Spencer Dinwiddie - 203915",
      "name": "Spencer Dinwiddie"
    },
    {
      "id": "Spencer Hawes - 201150",
      "name": "Spencer Hawes"
    },
    {
      "id": "Stanley Johnson - 1626169",
      "name": "Stanley Johnson"
    },
    {
      "id": "Stephen Curry - 201939",
      "name": "Stephen Curry"
    },
    {
      "id": "Stephen Zimmerman - 1627757",
      "name": "Stephen Zimmerman"
    },
    {
      "id": "Steve Novak - 200779",
      "name": "Steve Novak"
    },
    {
      "id": "Steven Adams - 203500",
      "name": "Steven Adams"
    },
    {
      "id": "T.J. McConnell - 204456",
      "name": "T.J. McConnell"
    },
    {
      "id": "T.J. Warren - 203933",
      "name": "T.J. Warren"
    },
    {
      "id": "Taj Gibson - 201959",
      "name": "Taj Gibson"
    },
    {
      "id": "Tarik Black - 204028",
      "name": "Tarik Black"
    },
    {
      "id": "Taurean Prince - 1627752",
      "name": "Taurean Prince"
    },
    {
      "id": "Terrence Jones - 203093",
      "name": "Terrence Jones"
    },
    {
      "id": "Terrence Ross - 203082",
      "name": "Terrence Ross"
    },
    {
      "id": "Terry Rozier - 1626179",
      "name": "Terry Rozier"
    },
    {
      "id": "Thabo Sefolosha - 200757",
      "name": "Thabo Sefolosha"
    },
    {
      "id": "Thaddeus Young - 201152",
      "name": "Thaddeus Young"
    },
    {
      "id": "Thomas Robinson - 203080",
      "name": "Thomas Robinson"
    },
    {
      "id": "Thon Maker - 1627748",
      "name": "Thon Maker"
    },
    {
      "id": "Tiago Splitter - 201168",
      "name": "Tiago Splitter"
    },
    {
      "id": "Tim Frazier - 204025",
      "name": "Tim Frazier"
    },
    {
      "id": "Tim Hardaway Jr. - 203501",
      "name": "Tim Hardaway Jr."
    },
    {
      "id": "Tim Quarterman - 1627817",
      "name": "Tim Quarterman"
    },
    {
      "id": "Timofey Mozgov - 202389",
      "name": "Timofey Mozgov"
    },
    {
      "id": "Timothe Luwawu-Cabarrot - 1627789",
      "name": "Timothe Luwawu-Cabarrot"
    },
    {
      "id": "Tobias Harris - 202699",
      "name": "Tobias Harris"
    },
    {
      "id": "Tomas Satoransky - 203107",
      "name": "Tomas Satoransky"
    },
    {
      "id": "Toney Douglas - 201962",
      "name": "Toney Douglas"
    },
    {
      "id": "Tony Allen - 2754",
      "name": "Tony Allen"
    },
    {
      "id": "Tony Parker - 2225",
      "name": "Tony Parker"
    },
    {
      "id": "Tony Snell - 203503",
      "name": "Tony Snell"
    },
    {
      "id": "Treveon Graham - 1626203",
      "name": "Treveon Graham"
    },
    {
      "id": "Trevor Ariza - 2772",
      "name": "Trevor Ariza"
    },
    {
      "id": "Trevor Booker - 202344",
      "name": "Trevor Booker"
    },
    {
      "id": "Trey Burke - 203504",
      "name": "Trey Burke"
    },
    {
      "id": "Trey Lyles - 1626168",
      "name": "Trey Lyles"
    },
    {
      "id": "Tristan Thompson - 202684",
      "name": "Tristan Thompson"
    },
    {
      "id": "Troy Daniels - 203584",
      "name": "Troy Daniels"
    },
    {
      "id": "Troy Williams - 1627786",
      "name": "Troy Williams"
    },
    {
      "id": "Ty Lawson - 201951",
      "name": "Ty Lawson"
    },
    {
      "id": "Tyler Ennis - 203898",
      "name": "Tyler Ennis"
    },
    {
      "id": "Tyler Johnson - 204020",
      "name": "Tyler Johnson"
    },
    {
      "id": "Tyler Ulis - 1627755",
      "name": "Tyler Ulis"
    },
    {
      "id": "Tyler Zeller - 203092",
      "name": "Tyler Zeller"
    },
    {
      "id": "Tyreke Evans - 201936",
      "name": "Tyreke Evans"
    },
    {
      "id": "Tyson Chandler - 2199",
      "name": "Tyson Chandler"
    },
    {
      "id": "Tyus Jones - 1626145",
      "name": "Tyus Jones"
    },
    {
      "id": "Udonis Haslem - 2617",
      "name": "Udonis Haslem"
    },
    {
      "id": "Victor Oladipo - 203506",
      "name": "Victor Oladipo"
    },
    {
      "id": "Vince Carter - 1713",
      "name": "Vince Carter"
    },
    {
      "id": "Wade Baldwin IV - 1627735",
      "name": "Wade Baldwin IV"
    },
    {
      "id": "Wayne Ellington - 201961",
      "name": "Wayne Ellington"
    },
    {
      "id": "Wayne Selden - 1627782",
      "name": "Wayne Selden"
    },
    {
      "id": "Wesley Johnson - 202325",
      "name": "Wesley Johnson"
    },
    {
      "id": "Wesley Matthews - 202083",
      "name": "Wesley Matthews"
    },
    {
      "id": "Will Barton - 203115",
      "name": "Will Barton"
    },
    {
      "id": "Willie Cauley-Stein - 1626161",
      "name": "Willie Cauley-Stein"
    },
    {
      "id": "Willie Reed - 203186",
      "name": "Willie Reed"
    },
    {
      "id": "Willy Hernangomez - 1626195",
      "name": "Willy Hernangomez"
    },
    {
      "id": "Wilson Chandler - 201163",
      "name": "Wilson Chandler"
    },
    {
      "id": "Yogi Ferrell - 1627812",
      "name": "Yogi Ferrell"
    },
    {
      "id": "Zach LaVine - 203897",
      "name": "Zach LaVine"
    },
    {
      "id": "Zach Randolph - 2216",
      "name": "Zach Randolph"
    },
    {
      "id": "Zaza Pachulia - 2585",
      "name": "Zaza Pachulia"
    }
  ],
  "teams": [
    {
      "name": "Atlanta Hawks"
    },
    {
      "name": "Boston Celtics"
    },
    {
      "name": "Brooklyn Nets"
    },
    {
      "name": "Charlotte Hornets"
    },
    {
      "name": "Chicago Bulls"
    },
    {
      "name": "Cleveland Cavaliers"
    },
    {
      "name": "Dallas Mavericks"
    },
    {
      "name": "Denver Nuggets"
    },
    {
      "name": "Detroit Pistons"
    },
    {
      "name": "Golden State Warriors"
    },
    {
      "name": "Houston Rockets"
    },
    {
      "name": "Indiana Pacers"
    },
    {
      "name": "LA Clippers"
    },
    {
      "name": "Los Angeles Lakers"
    },
    {
      "name": "Memphis Grizzlies"
    },
    {
      "name": "Miami Heat"
    },
    {
      "name": "Milwaukee Bucks"
    },
    {
      "name": "Minnesota Timberwolves"
    },
    {
      "name": "New Orleans Pelicans"
    },
    {
      "name": "New York Knicks"
    },
    {
      "name": "Oklahoma City Thunder"
    },
    {
      "name": "Orlando Magic"
    },
    {
      "name": "Philadelphia 76ers"
    },
    {
      "name": "Phoenix Suns"
    },
    {
      "name": "Portland Trail Blazers"
    },
    {
      "name": "Sacramento Kings"
    },
    {
      "name": "San Antonio Spurs"
    },
    {
      "name": "Toronto Raptors"
    },
    {
      "name": "Utah Jazz"
    },
    {
      "name": "Washington Wizards"
    }
  ],
  "generated_at": "2025-11-15 18:48:03",
  "total_players": 486,
  "total_teams": 30
}
